setup.py
STMB_FeatureSelection_primitive/STMBFeatSelector.py
STMB_FeatureSelection_primitive/STMB_FeatureSelection_primitive.ctf
STMB_FeatureSelection_primitive/__init__.py
STMB_FeatureSelection_primitive.egg-info/PKG-INFO
STMB_FeatureSelection_primitive.egg-info/SOURCES.txt
STMB_FeatureSelection_primitive.egg-info/dependency_links.txt
STMB_FeatureSelection_primitive.egg-info/top_level.txt