Metadata-Version: 1.0
Name: STMB-FeatureSelection-primitive
Version: 2.0.4
Summary: A module to call MATLAB from Python
Home-page: http://www.mathworks.com/
Author: MathWorks
Author-email: UNKNOWN
License: UNKNOWN
Platform: Linux
Platform: Windows
Platform: MacOS
